csrank/__init__.py
csrank/callbacks.py
csrank/constants.py
csrank/layers.py
csrank/learner.py
csrank/losses.py
csrank/metrics.py
csrank/metrics_np.py
csrank/numpy_util.py
csrank/tensorflow_util.py
csrank/theano_util.py
csrank/tunable.py
csrank/tuning.py
csrank/util.py
csrank/choicefunction/__init__.py
csrank/choicefunction/baseline.py
csrank/choicefunction/choice_functions.py
csrank/choicefunction/cmpnet_choice.py
csrank/choicefunction/fate_choice.py
csrank/choicefunction/fatelinear_choice.py
csrank/choicefunction/feta_choice.py
csrank/choicefunction/fetalinear_choice.py
csrank/choicefunction/generalized_linear_model.py
csrank/choicefunction/pairwise_choice.py
csrank/choicefunction/ranknet_choice.py
csrank/choicefunction/util.py
csrank/core/__init__.py
csrank/core/cmpnet_core.py
csrank/core/fate_linear.py
csrank/core/fate_network.py
csrank/core/feta_linear.py
csrank/core/feta_network.py
csrank/core/pairwise_svm.py
csrank/core/ranknet_core.py
csrank/dataset_reader/__init__.py
csrank/dataset_reader/dataset_reader.py
csrank/dataset_reader/expedia_dataset_reader.py
csrank/dataset_reader/letor_listwise_dataset_reader.py
csrank/dataset_reader/letor_ranking_dataset_reader.py
csrank/dataset_reader/mnist_dataset_reader.py
csrank/dataset_reader/sushi_dataset_reader.py
csrank/dataset_reader/synthetic_dataset_generator.py
csrank/dataset_reader/tag_genome_reader.py
csrank/dataset_reader/util.py
csrank/dataset_reader/choicefunctions/__init__.py
csrank/dataset_reader/choicefunctions/choice_data_generator.py
csrank/dataset_reader/choicefunctions/expedia_choice_dataset_reader.py
csrank/dataset_reader/choicefunctions/letor_ranking_choice_dataset_reader.py
csrank/dataset_reader/choicefunctions/mnist_choice_dataset_reader.py
csrank/dataset_reader/choicefunctions/util.py
csrank/dataset_reader/discretechoice/__init__.py
csrank/dataset_reader/discretechoice/discrete_choice_data_generator.py
csrank/dataset_reader/discretechoice/expedia_discrete_choice_dataset_reader.py
csrank-1.2.1.dist-info/LICENSE
csrank-1.2.1.dist-info/METADATA
csrank-1.2.1.dist-info/WHEEL
csrank-1.2.1.dist-info/top_level.txt
csrank-1.2.1.dist-info/RECORD
