Metadata-Version: 2.1
Name: csrank
Version: 1.2.1
Summary: Context-sensitive ranking
Home-page: https://github.com/kiudee/cs-ranking
Maintainer: Karlson Pfannschmidt
Maintainer-email: kiudee@mail.upb.de
License: UNKNOWN
Platform: UNKNOWN
Classifier: Development Status :: 4 - Beta
Classifier: Intended Audience :: Developers
Classifier: Intended Audience :: Science/Research
Classifier: License :: OSI Approved :: Apache Software License
Classifier: Natural Language :: English
Classifier: Programming Language :: Python :: 3
Classifier: Programming Language :: Python :: 3.6
Classifier: Programming Language :: Python :: 3.7
Classifier: Programming Language :: Python :: 3.8
Classifier: Topic :: Scientific/Engineering
Classifier: Topic :: Software Development
Requires-Dist: numpy (>=1.12.1)
Requires-Dist: scipy (>=0.19.0)
Requires-Dist: scikit-learn (>=0.18.2)
Requires-Dist: scikit-optimize (>=0.4)
Requires-Dist: pandas (>=0.22)
Requires-Dist: h5py (>=2.7)
Requires-Dist: docopt (>=0.6.0)
Requires-Dist: joblib (>=0.9.4)
Requires-Dist: tqdm (>=4.11.2)
Requires-Dist: keras (>=2.3)
Requires-Dist: tensorflow (<2.0,>=1.5)
Requires-Dist: psycopg2-binary (>=2.7)
Requires-Dist: pygmo (>=2.7)
Requires-Dist: pymc3 (>=3.8)
Requires-Dist: theano (>=1.0)
Provides-Extra: data
Requires-Dist: psycopg2-binary (>=2.7) ; extra == 'data'
Requires-Dist: pandas (>=0.22) ; extra == 'data'
Requires-Dist: h5py (>=2.7) ; extra == 'data'
Requires-Dist: pygmo (>=2.7) ; extra == 'data'
Provides-Extra: probabilistic
Requires-Dist: pymc3 (>=3.8) ; extra == 'probabilistic'
Requires-Dist: theano (>=1.0) ; extra == 'probabilistic'
